pyperfcheck/__init__.py
pyperfcheck/pyperfcheck.py
pyperfcheck-0.2.0.dist-info/METADATA
pyperfcheck-0.2.0.dist-info/WHEEL
pyperfcheck-0.2.0.dist-info/top_level.txt
pyperfcheck-0.2.0.dist-info/RECORD
