Metadata-Version: 2.2
Name: pyperfcheck
Version: 0.2.0
Summary: A high-performance benchmarking library for Python
Home-page: https://github.com/Janardhan11/pyperfcheck
Author: Janardhan Medathati
Author-email: 7janardhan7@gmail.com
Classifier: Programming Language :: Python :: 3
Classifier: License :: OSI Approved :: MIT License
Classifier: Programming Language :: Python :: 3.9
Classifier: Operating System :: OS Independent
Requires-Python: >=3.6
Requires-Dist: psutil
Requires-Dist: matplotlib
Requires-Dist: tabulate
Requires-Dist: asyncio
Dynamic: author
Dynamic: author-email
Dynamic: classifier
Dynamic: description
Dynamic: description-content-type
Dynamic: home-page
Dynamic: requires-dist
Dynamic: requires-python
Dynamic: summary
